rassumfrassum/__init__.py
rassumfrassum/__main__.py
rassumfrassum/frassum.py
rassumfrassum/json.py
rassumfrassum/main.py
rassumfrassum/preset.py
rassumfrassum/rassum.py
rassumfrassum/stdio.py
rassumfrassum/test2.py
rassumfrassum/util.py
rassumfrassum/presets/__init__.py
rassumfrassum/presets/basedruff.py
rassumfrassum/presets/python.py
rassumfrassum/presets/tslint.py
rassumfrassum/presets/tyruff.py
rassumfrassum/presets/vuetail.py
rassumfrassum-0.3.3.dist-info/licenses/LICENSE
rassumfrassum-0.3.3.dist-info/METADATA
rassumfrassum-0.3.3.dist-info/WHEEL
rassumfrassum-0.3.3.dist-info/entry_points.txt
rassumfrassum-0.3.3.dist-info/top_level.txt
rassumfrassum-0.3.3.dist-info/RECORD
