Metadata-Version: 2.4
Name: rassumfrassum
Version: 0.3.3
Summary: LSP/JSONRPC multiplexer for connecting one LSP client to multiple servers
Author-email: João Távora <joaotavora@gmail.com>
Project-URL: Homepage, https://github.com/joaotavora/rassumfrassum
Project-URL: Issues, https://github.com/joaotavora/rassumfrassum/issues
Keywords: lsp,language-server-protocol,multiplexer,jsonrpc
Classifier: Programming Language :: Python :: 3
Classifier: Programming Language :: Python :: 3.10
Classifier: Programming Language :: Python :: 3.11
Classifier: Programming Language :: Python :: 3.12
Classifier: Programming Language :: Python :: 3.13
Classifier: License :: OSI Approved :: GNU General Public License v3 or later (GPLv3+)
Classifier: Operating System :: OS Independent
Classifier: Development Status :: 3 - Alpha
Classifier: Intended Audience :: Developers
Classifier: Topic :: Software Development :: Libraries :: Python Modules
Requires-Python: >=3.10
License-File: LICENSE
Dynamic: license-file
